python_filmaffinity/__init__.py
python_filmaffinity/__meta__.py
python_filmaffinity/client.py
python_filmaffinity/config.py
python_filmaffinity/exceptions.py
python_filmaffinity/proxies.py
python_filmaffinity/pages/__init__.py
python_filmaffinity/pages/detail.py
python_filmaffinity/pages/images.py
python_filmaffinity/pages/page.py
python_filmaffinity/pages/search.py
python_filmaffinity/pages/top.py
python_filmaffinity/pages/top_service.py
python_filmaffinity-0.0.19.dist-info/AUTHORS.rst
python_filmaffinity-0.0.19.dist-info/LICENSE.rst
python_filmaffinity-0.0.19.dist-info/METADATA
python_filmaffinity-0.0.19.dist-info/WHEEL
python_filmaffinity-0.0.19.dist-info/top_level.txt
python_filmaffinity-0.0.19.dist-info/RECORD
