Metadata-Version: 2.1
Name: python-filmaffinity
Version: 0.0.19
Summary: Python wrapper for FilmAffinity
Home-page: https://github.com/sergiormb/python_filmaffinity
Author: sergiormb
Author-email: sergiormb88@gmail.com
License: MIT License
Download-URL: https://github.com/sergiormb/python_filmaffinity/tarball/0.0.19
Keywords: filmaffinity movies films
Platform: UNKNOWN
Classifier: Environment :: Web Environment
Classifier: Intended Audience :: Developers
Classifier: Operating System :: OS Independent
Classifier: Programming Language :: Python
Classifier: License :: OSI Approved :: MIT License
Classifier: Programming Language :: Python
Classifier: Programming Language :: Python :: 3
Classifier: Programming Language :: Python :: 3.2
Classifier: Programming Language :: Python :: 3.3
Classifier: Programming Language :: Python :: 3.4
Requires-Dist: requests (>=2.24.0)
Requires-Dist: requests-cache (>=0.5.2)
Requires-Dist: bs4 (>=0.0.1)
Requires-Dist: user-agent (==0.1.9)
